[
  {"word": "frog", "hint": "small green jumper"},
  {"word": "moon", "hint": "shines at night"},
  {"word": "rose", "hint": "a flower with thorns"},
  {"word": "gold", "hint": "shiny precious metal"},
  {"word": "wolf", "hint": "wild canine"},
  {"word": "snow", "hint": "frozen white flakes"},
  {"word": "ship", "hint": "sails on the sea"},
  {"word": "star", "hint": "twinkles in the sky"},
  {"word": "lion", "hint": "king of the jungle"},
  {"word": "cake", "hint": "sweet baked treat"},
  
  {"word": "apple", "hint": "keeps the doctor away"},
  {"word": "train", "hint": "runs on tracks"},
  {"word": "earth", "hint": "our planet"},
  {"word": "camel", "hint": "desert traveler"},
  {"word": "grape", "hint": "grows in bunches"},
  {"word": "whale", "hint": "giant ocean mammal"},
  {"word": "tiger", "hint": "striped big cat"},
  {"word": "zebra", "hint": "black and white stripes"},
  {"word": "pearl", "hint": "jewel from an oyster"},
  {"word": "flame", "hint": "tiny dancing fire"},
  
  {"word": "forest", "hint": "full of trees"},
  {"word": "puzzle", "hint": "tricky brain teaser"},
  {"word": "stream", "hint": "small flowing water"},
  {"word": "silver", "hint": "shiny gray metal"},
  {"word": "banana", "hint": "yellow fruit"},
  {"word": "parrot", "hint": "colorful talking bird"},
  {"word": "planet", "hint": "orbits a star"},
  {"word": "cookie", "hint": "crunchy sweet snack"},
  {"word": "monkey", "hint": "banana lover"},
  
  {"word": "lemon", "hint": "sour yellow fruit"},
  {"word": "piano", "hint": "88 keys instrument"},
  {"word": "honey", "hint": "made by bees"},
  {"word": "brick", "hint": "builds a wall"},
  {"word": "flock", "hint": "group of birds"},
  {"word": "cloud", "hint": "floats in the sky"},
  {"word": "berry", "hint": "small juicy fruit"},
  {"word": "robot", "hint": "machine helper"},
  {"word": "cabin", "hint": "small wooden house"},
  {"word": "shark", "hint": "fearsome ocean fish"},
  
  {"word": "globe", "hint": "small round world"},
  {"word": "crane", "hint": "tall lifting machine"},
  {"word": "flute", "hint": "wind instrument"},
  {"word": "crown", "hint": "worn by a king"},
  {"word": "sheep", "hint": "woolly farm animal"},
  {"word": "sugar", "hint": "makes things sweet"},
  {"word": "bread", "hint": "baked daily staple"},
  {"word": "mango", "hint": "tropical orange fruit"},
  {"word": "melon", "hint": "juicy summer fruit"},
  {"word": "torch", "hint": "handheld light"},
  
  {"word": "comet", "hint": "icy space traveler"},
  {"word": "jewel", "hint": "precious stone"},
  {"word": "raven", "hint": "black clever bird"},
  {"word": "toast", "hint": "crispy bread"},
  {"word": "grill", "hint": "cooks over flames"},
  {"word": "mouse", "hint": "tiny squeaker"},
  {"word": "lakes", "hint": "large bodies of water"},
  {"word": "badge", "hint": "worn for honor"},
  {"word": "ocean", "hint": "vast blue water"},
  {"word": "tulip", "hint": "spring bulb flower"}
]
